tfhub_styletransfer_wrapper/__init__.py
tfhub_styletransfer_wrapper/hubFnc.py
tfhub_styletransfer_wrapper/imgFnc.py
tfhub_styletransfer_wrapper-1.1.3.dist-info/LICENSE
tfhub_styletransfer_wrapper-1.1.3.dist-info/METADATA
tfhub_styletransfer_wrapper-1.1.3.dist-info/WHEEL
tfhub_styletransfer_wrapper-1.1.3.dist-info/top_level.txt
tfhub_styletransfer_wrapper-1.1.3.dist-info/RECORD
