Metadata-Version: 2.1
Name: tfhub-styletransfer-wrapper
Version: 1.1.3
Summary: A wrapper that contains quick functions to load and process data with Googles TF Hub v2 fast arbitrary image style transfer model
Home-page: https://github.com/alex-parisi/tfhub-styletransfer-wrapper
Author: Alex Parisi
Author-email: alex.parisi@outlook.com
License: UNKNOWN
Project-URL: Bug Tracker, https://github.com/alex-parisi/tfhub-styletransfer-wrapper/issues
Platform: UNKNOWN
Classifier: Programming Language :: Python :: 3
Classifier: License :: OSI Approved :: MIT License
Classifier: Operating System :: OS Independent
Requires-Python: >=3.7
License-File: LICENSE
Requires-Dist: tensorflow (==2.7.0)
Requires-Dist: tensorflow-hub (==0.12.0)
Requires-Dist: matplotlib (==3.5.1)
Requires-Dist: opencv-python (==4.5.5.62)
Requires-Dist: imageio (==2.14.1)
